odoo9_addon_stock_pack_operation_quick_lot-9.0.1.0.0.99.dev2-py2.7-nspkg.pth
odoo9_addon_stock_pack_operation_quick_lot-9.0.1.0.0.99.dev2.dist-info/METADATA
odoo9_addon_stock_pack_operation_quick_lot-9.0.1.0.0.99.dev2.dist-info/RECORD
odoo9_addon_stock_pack_operation_quick_lot-9.0.1.0.0.99.dev2.dist-info/WHEEL
odoo9_addon_stock_pack_operation_quick_lot-9.0.1.0.0.99.dev2.dist-info/namespace_packages.txt
odoo9_addon_stock_pack_operation_quick_lot-9.0.1.0.0.99.dev2.dist-info/top_level.txt
odoo_addons/stock_pack_operation_quick_lot/README.rst
odoo_addons/stock_pack_operation_quick_lot/__init__.py
odoo_addons/stock_pack_operation_quick_lot/__openerp__.py
odoo_addons/stock_pack_operation_quick_lot/i18n/es.po
odoo_addons/stock_pack_operation_quick_lot/i18n/stock_pack_operation_quick_lot.pot
odoo_addons/stock_pack_operation_quick_lot/models/__init__.py
odoo_addons/stock_pack_operation_quick_lot/models/stock_pack_operation.py
odoo_addons/stock_pack_operation_quick_lot/static/description/icon.png
odoo_addons/stock_pack_operation_quick_lot/static/description/icon.svg
odoo_addons/stock_pack_operation_quick_lot/tests/__init__.py
odoo_addons/stock_pack_operation_quick_lot/tests/test_pack_operation_quick_lot.py
odoo_addons/stock_pack_operation_quick_lot/views/stock_view.xml
